{
  "config": {
    "project_name": "Implementación Servicio Auditoría Cíclica de Inventarios - Cheeky",
    "client_name": "Cheeky S.A.",
    "start_date": "2026-08-01",
    "end_date": "2026-09-25",
    "status": "En proceso"
  },
  "tasks": [
    { "id": 1, "stage": "Diagnóstico Inicial y Matriz ABC", "activity": "Kickoff del proyecto ACAI-Cheeky", "responsible": "Martina Ibáñez", "priority": "Alta", "start_date": "2026-08-01", "end_date": "2026-08-02", "status": "Finalizado", "progress": 100 },
    { "id": 2, "stage": "Diagnóstico Inicial y Matriz ABC", "activity": "Extracción de catálogo maestro SKU (talle/color) del ERP", "responsible": "Bruno Castellano", "priority": "Alta", "start_date": "2026-08-02", "end_date": "2026-08-03", "status": "Finalizado", "progress": 100 },
    { "id": 3, "stage": "Diagnóstico Inicial y Matriz ABC", "activity": "Definición de matriz ABC por costo y rotación", "responsible": "Federico Suárez", "priority": "Alta", "start_date": "2026-08-03", "end_date": "2026-08-05", "status": "Finalizado", "progress": 100 },
    { "id": 4, "stage": "Diagnóstico Inicial y Matriz ABC", "activity": "Selección de muestra de sucursales y SKUs críticos", "responsible": "Martina Ibáñez", "priority": "Media", "start_date": "2026-08-04", "end_date": "2026-08-05", "status": "Finalizado", "progress": 100 },
    { "id": 5, "stage": "Diagnóstico Inicial y Matriz ABC", "activity": "Cruce de catálogo de variantes talle/color vs. codificación de góndola", "responsible": "Federico Suárez", "priority": "Alta", "start_date": "2026-08-05", "end_date": "2026-08-07", "status": "Finalizado", "progress": 100 },
    { "id": 6, "stage": "Diagnóstico Inicial y Matriz ABC", "activity": "Informe de diagnóstico inicial y línea base", "responsible": "Martina Ibáñez", "priority": "Crítica", "start_date": "2026-08-07", "end_date": "2026-08-09", "status": "Finalizado", "progress": 100 },
    { "id": 7, "stage": "Diseño de Protocolo SOP y Calibración", "activity": "Diseño de SOP de auditoría cíclica de 2 horas en tienda", "responsible": "Federico Suárez", "priority": "Crítica", "start_date": "2026-08-10", "end_date": "2026-08-12", "status": "Finalizado", "progress": 100 },
    { "id": 8, "stage": "Diseño de Protocolo SOP y Calibración", "activity": "Diseño de hoja de conteo ciego (doble conteo)", "responsible": "Federico Suárez", "priority": "Media", "start_date": "2026-08-12", "end_date": "2026-08-13", "status": "Finalizado", "progress": 100 },
    { "id": 9, "stage": "Diseño de Protocolo SOP y Calibración", "activity": "Configuración y prueba de colectores/scanners RF", "responsible": "Bruno Castellano", "priority": "Alta", "start_date": "2026-08-13", "end_date": "2026-08-15", "status": "Finalizado", "progress": 100 },
    { "id": 10, "stage": "Diseño de Protocolo SOP y Calibración", "activity": "Capacitación a auditores de campo en protocolo SOP", "responsible": "Federico Suárez", "priority": "Alta", "start_date": "2026-08-15", "end_date": "2026-08-17", "status": "Finalizado", "progress": 100 },
    { "id": 11, "stage": "Diseño de Protocolo SOP y Calibración", "activity": "Validación del protocolo con Gerencia de Operaciones", "responsible": "Lucía Fernández", "priority": "Media", "start_date": "2026-08-17", "end_date": "2026-08-19", "status": "Finalizado", "progress": 100 },
    { "id": 12, "stage": "Piloto en Tiendas Críticas", "activity": "Auditoría piloto Tienda Alto Palermo (2hs)", "responsible": "Federico Suárez", "priority": "Crítica", "start_date": "2026-08-20", "end_date": "2026-08-20", "status": "Finalizado", "progress": 100 },
    { "id": 13, "stage": "Piloto en Tiendas Críticas", "activity": "Análisis de descalces Tienda Alto Palermo", "responsible": "Federico Suárez", "priority": "Alta", "start_date": "2026-08-21", "end_date": "2026-08-22", "status": "Finalizado", "progress": 100 },
    { "id": 14, "stage": "Piloto en Tiendas Críticas", "activity": "Auditoría piloto Tienda Unicenter (2hs)", "responsible": "Federico Suárez", "priority": "Crítica", "start_date": "2026-08-24", "end_date": "2026-08-24", "status": "Finalizado", "progress": 100 },
    { "id": 15, "stage": "Piloto en Tiendas Críticas", "activity": "Análisis de descalces Tienda Unicenter", "responsible": "Federico Suárez", "priority": "Alta", "start_date": "2026-08-25", "end_date": "2026-08-26", "status": "En proceso", "progress": 50 },
    { "id": 16, "stage": "Piloto en Tiendas Críticas", "activity": "Auditoría piloto Tienda DOT Baires (2hs)", "responsible": "Federico Suárez", "priority": "Crítica", "start_date": "2026-08-28", "end_date": "2026-08-28", "status": "No iniciado", "progress": 0 },
    { "id": 17, "stage": "Piloto en Tiendas Críticas", "activity": "Análisis de descalces Tienda DOT Baires", "responsible": "Federico Suárez", "priority": "Alta", "start_date": "2026-08-29", "end_date": "2026-08-31", "status": "No iniciado", "progress": 0 },
    { "id": 18, "stage": "Piloto en Tiendas Críticas", "activity": "Consolidado de resultados del piloto (3 tiendas)", "responsible": "Martina Ibáñez", "priority": "Alta", "start_date": "2026-09-01", "end_date": "2026-09-02", "status": "No iniciado", "progress": 0 },
    { "id": 19, "stage": "Análisis de Causa Raíz y Matriz de Descalce", "activity": "Construcción de matriz de descalce por tipo de falla", "responsible": "Federico Suárez", "priority": "Alta", "start_date": "2026-09-03", "end_date": "2026-09-05", "status": "No iniciado", "progress": 0 },
    { "id": 20, "stage": "Análisis de Causa Raíz y Matriz de Descalce", "activity": "Clasificación de causas: error de recepción en muelle", "responsible": "Bruno Castellano", "priority": "Media", "start_date": "2026-09-05", "end_date": "2026-09-07", "status": "No iniciado", "progress": 0 },
    { "id": 21, "stage": "Análisis de Causa Raíz y Matriz de Descalce", "activity": "Clasificación de causas: cruce de variantes en POS", "responsible": "Federico Suárez", "priority": "Alta", "start_date": "2026-09-05", "end_date": "2026-09-07", "status": "No iniciado", "progress": 0 },
    { "id": 22, "stage": "Análisis de Causa Raíz y Matriz de Descalce", "activity": "Clasificación de causas: ubicación fantasma en backroom", "responsible": "Federico Suárez", "priority": "Media", "start_date": "2026-09-07", "end_date": "2026-09-09", "status": "No iniciado", "progress": 0 },
    { "id": 23, "stage": "Análisis de Causa Raíz y Matriz de Descalce", "activity": "Clasificación de causas: merma no identificada", "responsible": "Bruno Castellano", "priority": "Alta", "start_date": "2026-09-09", "end_date": "2026-09-11", "status": "No iniciado", "progress": 0 },
    { "id": 24, "stage": "Análisis de Causa Raíz y Matriz de Descalce", "activity": "Diseño del Plan de Acción Correctivo (CAP) por causa raíz", "responsible": "Martina Ibáñez", "priority": "Crítica", "start_date": "2026-09-11", "end_date": "2026-09-16", "status": "No iniciado", "progress": 0 },
    { "id": 25, "stage": "Institucionalización y Handover", "activity": "Diseño del Scorecard Ejecutivo de Inventario", "responsible": "Martina Ibáñez", "priority": "Alta", "start_date": "2026-09-17", "end_date": "2026-09-19", "status": "No iniciado", "progress": 0 },
    { "id": 26, "stage": "Institucionalización y Handover", "activity": "Presentación del Scorecard a Gerencia Cheeky", "responsible": "Martina Ibáñez", "priority": "Crítica", "start_date": "2026-09-21", "end_date": "2026-09-21", "status": "No iniciado", "progress": 0 },
    { "id": 27, "stage": "Institucionalización y Handover", "activity": "Definición de calendario de recurrencia de auditoría cíclica", "responsible": "Federico Suárez", "priority": "Media", "start_date": "2026-09-22", "end_date": "2026-09-23", "status": "No iniciado", "progress": 0 },
    { "id": 28, "stage": "Institucionalización y Handover", "activity": "Informe final y cierre de proyecto ACAI-Cheeky", "responsible": "Martina Ibáñez", "priority": "Crítica", "start_date": "2026-09-24", "end_date": "2026-09-25", "status": "No iniciado", "progress": 0 }
  ],
  "plan_stages": [
    { "id": 1, "stage": "Diagnóstico Inicial y Matriz ABC", "activity_id": "D-1", "activity": "Extracción y cruce de catálogo maestro (talle/color)", "description": "Consolidación del catálogo ERP vs. codificación de piso de venta", "deliverable": "Catálogo maestro consolidado", "estimated_duration": "3 días", "dependencies": "", "completed": true },
    { "id": 2, "stage": "Diagnóstico Inicial y Matriz ABC", "activity_id": "D-2", "activity": "Matriz ABC y selección de muestra", "description": "Segmentación de SKUs/tiendas críticos y línea base de KPIs", "deliverable": "Informe de diagnóstico y línea base", "estimated_duration": "4 días", "dependencies": "D-1", "completed": true },
    { "id": 3, "stage": "Diseño de Protocolo SOP y Calibración", "activity_id": "P-1", "activity": "Diseño de SOP y hoja de conteo ciego", "description": "Procedimiento estándar de auditoría cíclica de 2 horas", "deliverable": "SOP aprobado", "estimated_duration": "4 días", "dependencies": "D-2", "completed": true },
    { "id": 4, "stage": "Diseño de Protocolo SOP y Calibración", "activity_id": "P-2", "activity": "Calibración de colectores y capacitación a auditores", "description": "Puesta a punto de dispositivos y entrenamiento del equipo", "deliverable": "Equipo capacitado y colectores calibrados", "estimated_duration": "5 días", "dependencies": "P-1", "completed": true },
    { "id": 5, "stage": "Piloto en Tiendas Críticas", "activity_id": "PI-1", "activity": "Piloto Tienda Alto Palermo", "description": "Auditoría y análisis de descalce en primera tienda piloto", "deliverable": "Informe de descalce Tienda 1", "estimated_duration": "3 días", "dependencies": "P-2", "completed": true },
    { "id": 6, "stage": "Piloto en Tiendas Críticas", "activity_id": "PI-2", "activity": "Piloto Tienda Unicenter", "description": "Auditoría y análisis de descalce en segunda tienda piloto", "deliverable": "Informe de descalce Tienda 2", "estimated_duration": "3 días", "dependencies": "PI-1", "completed": false },
    { "id": 7, "stage": "Piloto en Tiendas Críticas", "activity_id": "PI-3", "activity": "Piloto Tienda DOT Baires y consolidado", "description": "Auditoría en tercera tienda y consolidado de las 3 tiendas", "deliverable": "Informe consolidado de piloto", "estimated_duration": "6 días", "dependencies": "PI-2", "completed": false },
    { "id": 8, "stage": "Análisis de Causa Raíz y Matriz de Descalce", "activity_id": "CR-1", "activity": "Matriz de descalce y clasificación de causas", "description": "Clasificación por error de recepción, cruce POS, ubicación fantasma y merma", "deliverable": "Matriz de causa raíz", "estimated_duration": "2 semanas", "dependencies": "PI-3", "completed": false },
    { "id": 9, "stage": "Análisis de Causa Raíz y Matriz de Descalce", "activity_id": "CR-2", "activity": "Diseño del Plan de Acción Correctivo (CAP)", "description": "Definición de acciones correctivas priorizadas por impacto monetario", "deliverable": "CAP aprobado", "estimated_duration": "1 semana", "dependencies": "CR-1", "completed": false },
    { "id": 10, "stage": "Institucionalización y Handover", "activity_id": "H-1", "activity": "Scorecard Ejecutivo y presentación a Gerencia", "description": "Tablero de indicadores y presentación de resultados a Dirección", "deliverable": "Scorecard aprobado", "estimated_duration": "1 semana", "dependencies": "CR-2", "completed": false },
    { "id": 11, "stage": "Institucionalización y Handover", "activity_id": "H-2", "activity": "Calendario de recurrencia e informe final", "description": "Cronograma de auditoría cíclica permanente y cierre del proyecto", "deliverable": "Informe final de cierre", "estimated_duration": "1 semana", "dependencies": "H-1", "completed": false }
  ],
  "risks": [
    { "id": 1, "risk": "Resistencia del personal de tienda a ser auditado en horario comercial", "category": "Organizacional", "probability": "Alta", "impact": "Alto", "level": "CRÍTICO", "responsible": "Federico Suárez", "mitigation": "Programar auditorías en horarios de menor tráfico y comunicar previamente a encargados", "status": "Activo" },
    { "id": 2, "risk": "Inconsistencia de datos teóricos en el ERP de Cheeky al momento de la extracción", "category": "Tecnológico", "probability": "Media", "impact": "Alto", "level": "CRÍTICO", "responsible": "Bruno Castellano", "mitigation": "Validar extracción con corte de operaciones (freeze) antes de cada auditoría", "status": "Activo" },
    { "id": 3, "risk": "Alta rotación de personal de cajas que perpetúa cruces de SKU talle/color", "category": "Organizacional", "probability": "Alta", "impact": "Medio", "level": "MEDIO", "responsible": "Lucía Fernández", "mitigation": "Reforzar capacitación en POS para nuevos ingresos", "status": "Activo" },
    { "id": 4, "risk": "Discrepancias entre conteo físico y colector RF por fallas de lectura de etiqueta", "category": "Tecnológico", "probability": "Media", "impact": "Medio", "level": "MEDIO", "responsible": "Federico Suárez", "mitigation": "Doble conteo ciego como control cruzado", "status": "Mitigado" },
    { "id": 5, "risk": "Indisponibilidad de personal de tienda para acompañar la auditoría", "category": "Operativo", "probability": "Media", "impact": "Bajo", "level": "BAJO", "responsible": "Lucía Fernández", "mitigation": "Coordinar agenda con una semana de anticipación", "status": "Activo" },
    { "id": 6, "risk": "Resistencia a implementar el Plan de Acción Correctivo por sobrecarga operativa de tiendas", "category": "Organizacional", "probability": "Media", "impact": "Alto", "level": "CRÍTICO", "responsible": "Martina Ibáñez", "mitigation": "Priorizar CAP por impacto monetario e involucrar a Gerencia desde el diseño", "status": "Activo" }
  ],
  "minutes": [
    { "id": 1, "meeting_date": "2026-08-01", "meeting_type": "Kickoff", "topic": "Arranque del proyecto ACAI-Cheeky", "decisions": "Se aprueba alcance, cronograma de 8 semanas y las 3 tiendas piloto (Alto Palermo, Unicenter, DOT Baires)", "actions": "Enviar catálogo maestro ERP y accesos a colectores RF", "responsible": "Martina Ibáñez", "status": "Cerrada" },
    { "id": 2, "meeting_date": "2026-08-22", "meeting_type": "Revisión de Piloto", "topic": "Revisión de resultados del piloto en Tienda Alto Palermo", "decisions": "Se detecta 8% de descalce monetario neto, mayormente por cruce de talle/color en POS; se ajusta protocolo de conteo en percheros", "actions": "Ajustar hoja de conteo ciego para separar por variante antes del piloto en Unicenter", "responsible": "Federico Suárez", "status": "Cerrada" },
    { "id": 3, "meeting_date": "2026-09-02", "meeting_type": "Presentación Preliminar", "topic": "Presentación preliminar de hallazgos de causa raíz del piloto", "decisions": "Se prioriza el Plan de Acción Correctivo sobre errores de recepción en muelle", "actions": "Convocar a Jefe de Recepción y Logística a la próxima etapa de análisis", "responsible": "Martina Ibáñez", "status": "En curso" }
  ],
  "actions": [
    { "id": 1, "action_name": "Enviar catálogo maestro ERP y accesos a colectores RF", "stage": "Diagnóstico Inicial y Matriz ABC", "responsible": "Bruno Castellano", "priority": "Alta", "commitment_date": "2026-08-04", "status": "Cerrada", "progress": 100, "origin": "Minuta" },
    { "id": 2, "action_name": "Ajustar hoja de conteo ciego para separar por variante talle/color", "stage": "Piloto en Tiendas Críticas", "responsible": "Federico Suárez", "priority": "Alta", "commitment_date": "2026-08-24", "status": "Cerrada", "progress": 100, "origin": "Minuta" },
    { "id": 3, "action_name": "Convocar a Jefe de Recepción y Logística Cheeky a la etapa de causa raíz", "stage": "Análisis de Causa Raíz y Matriz de Descalce", "responsible": "Martina Ibáñez", "priority": "Media", "commitment_date": "2026-09-05", "status": "En curso", "progress": 40, "origin": "Minuta" },
    { "id": 4, "action_name": "Solicitar reporte de mermas de los últimos 6 meses a Loss Prevention", "stage": "Análisis de Causa Raíz y Matriz de Descalce", "responsible": "Bruno Castellano", "priority": "Alta", "commitment_date": "2026-09-08", "status": "No iniciada", "progress": 0, "origin": "Gestión de riesgos" },
    { "id": 5, "action_name": "Coordinar agenda de auditoría en tiendas con encargados suplentes", "stage": "Piloto en Tiendas Críticas", "responsible": "Lucía Fernández", "priority": "Media", "commitment_date": "2026-08-27", "status": "En curso", "progress": 50, "origin": "Gestión de riesgos" },
    { "id": 6, "action_name": "Preparar propuesta de calendario de recurrencia trimestral", "stage": "Institucionalización y Handover", "responsible": "Federico Suárez", "priority": "Media", "commitment_date": "2026-09-20", "status": "No iniciada", "progress": 0, "origin": "Manual" }
  ],
  "kpis": [
    { "id": 1, "category": "Precisión de Inventario", "indicator": "Exactitud de Registro de Inventario (IRA)", "unit": "%", "initial_value": 82.0, "target_value": 96.0, "current_value": 85.0, "responsible": "Federico Suárez" },
    { "id": 2, "category": "Tiempos", "indicator": "Tiempo medio de relevamiento por sucursal", "unit": "min", "initial_value": 165, "target_value": 120, "current_value": 148, "responsible": "Federico Suárez" },
    { "id": 3, "category": "Financiero", "indicator": "% de Descalce Monetario Neto", "unit": "%", "initial_value": 6.8, "target_value": 1.5, "current_value": 5.4, "responsible": "Bruno Castellano" },
    { "id": 4, "category": "Backroom", "indicator": "Ratio de Ubicaciones Fantasma en Backroom", "unit": "%", "initial_value": 12.0, "target_value": 2.0, "current_value": 9.5, "responsible": "Bruno Castellano" },
    { "id": 5, "category": "Calidad POS", "indicator": "Errores de Lectura por Cruce de Talle/Color en POS", "unit": "%", "initial_value": 9.5, "target_value": 2.0, "current_value": 7.8, "responsible": "Lucía Fernández" },
    { "id": 6, "category": "Cumplimiento", "indicator": "% de Cumplimiento del Plan de Acción Correctivo (CAP)", "unit": "%", "initial_value": 0, "target_value": 90, "current_value": 15, "responsible": "Martina Ibáñez" },
    { "id": 7, "category": "Recepción", "indicator": "Mermas no identificadas en muelle de recepción", "unit": "%", "initial_value": 4.2, "target_value": 1.0, "current_value": 3.6, "responsible": "Bruno Castellano" },
    { "id": 8, "category": "Servicio", "indicator": "Quiebres de Stock Falsos (Stock Fantasma)", "unit": "%", "initial_value": 11.0, "target_value": 3.0, "current_value": 8.9, "responsible": "Lucía Fernández" }
  ],
  "before_after": [
    { "id": 1, "area": "Operaciones", "indicator": "Tiempo de paro para conteo físico anual", "unit": "horas/año", "initial_value": 24, "final_value": null, "observations": "Objetivo proyectado: 0h con conteo cíclico permanente, sin cierre de tienda" },
    { "id": 2, "area": "Inventario", "indicator": "Exactitud de Registro de Inventario (IRA)", "unit": "%", "initial_value": 82.0, "final_value": null, "observations": "Objetivo proyectado: 96%, medición final al cierre del proyecto" },
    { "id": 3, "area": "Ventas", "indicator": "Pérdida mensual por ventas canceladas por stock fantasma", "unit": "USD/mes", "initial_value": 42000, "final_value": null, "observations": "Reducción proyectada de ~70% tras implementación del CAP" },
    { "id": 4, "area": "Recepción", "indicator": "Mermas no identificadas en muelle de recepción", "unit": "%", "initial_value": 4.2, "final_value": null, "observations": "Medición final tras institucionalización del protocolo" },
    { "id": 5, "area": "Backroom", "indicator": "Ubicaciones fantasma en backroom", "unit": "%", "initial_value": 12.0, "final_value": null, "observations": "Medición final tras el primer ciclo de recurrencia trimestral" }
  ],
  "team_members": [
    { "id": 1, "name": "Martina Ibáñez", "role": "Líder de Proyecto CDI", "email": "martina.ibanez@cdiconsultoria.com", "color": "#1e3a5f" },
    { "id": 2, "name": "Federico Suárez", "role": "Auditor Senior de Campo CDI", "email": "federico.suarez@cdiconsultoria.com", "color": "#38a169" },
    { "id": 3, "name": "Lucía Fernández", "role": "Gerente de Operaciones Cheeky", "email": "lucia.fernandez@cheeky.com.ar", "color": "#d69e2e" },
    { "id": 4, "name": "Bruno Castellano", "role": "Jefe de Inventarios Cheeky", "email": "bruno.castellano@cheeky.com.ar", "color": "#2c5282" }
  ]
}
